Crawler/BaseMethod.py
Crawler/Javdb.py
Crawler/__init__.py
Util/FileProcess.py
Util/Mysqlite.py
Util/__init__.py
chaotools18-0.1.2.dist-info/LICENSE
chaotools18-0.1.2.dist-info/METADATA
chaotools18-0.1.2.dist-info/WHEEL
chaotools18-0.1.2.dist-info/top_level.txt
chaotools18-0.1.2.dist-info/RECORD
