Metadata-Version: 2.1
Name: chaotools18
Version: 0.1.2
Summary: chaotools18
Home-page: UNKNOWN
Author: chao
License: UNKNOWN
Platform: UNKNOWN
Classifier: Programming Language :: Python :: 3
Classifier: License :: OSI Approved :: MIT License
Classifier: Operating System :: OS Independent
